README.md
setup.py
open3d_plus/__init__.py
open3d_plus/geometry.py
open3d_plus/vis.py
open3d_plus.egg-info/PKG-INFO
open3d_plus.egg-info/SOURCES.txt
open3d_plus.egg-info/dependency_links.txt
open3d_plus.egg-info/requires.txt
open3d_plus.egg-info/top_level.txt
tests/test_create_axis.py
tests/test_pcd.py
tests/test_render.py