Metadata-Version: 2.1
Name: open3d_plus
Version: 0.3.3
Summary: open3d plus functions
Home-page: 
Author: Minghao Gou
Author-email: gouminghao@gmail.com
Requires-Dist: numpy
Requires-Dist: open3d
Requires-Dist: opencv-python
Requires-Dist: matplotlib
